giossync/__init__.py
giossync/test.py
giossync-0.0.3.dist-info/LICENSE
giossync-0.0.3.dist-info/METADATA
giossync-0.0.3.dist-info/WHEEL
giossync-0.0.3.dist-info/top_level.txt
giossync-0.0.3.dist-info/RECORD
